sisal/__init__.py
sisal/_version.py
sisal/kernel_adapted.py
sisal/model.py
sisal/plot.py
sisal/py.typed
sisal/solver.py
sisal/utils.py
sisal-0.1.0.dist-info/licenses/LICENSE
sisal-0.1.0.dist-info/METADATA
sisal-0.1.0.dist-info/WHEEL
sisal-0.1.0.dist-info/top_level.txt
sisal-0.1.0.dist-info/RECORD
