Metadata-Version: 2.4
Name: sisal
Version: 0.1.0
Summary: Beta-variational autoencoder for IMS (and other) data.
Author-email: Paul-Louis Delacour <delacourpaullouis@gmail.com>
License: BSD 3-Clause License
Project-URL: homepage, https://github.com/pauldelacour/sisal
Project-URL: repository, https://github.com/pauldelacour/sisal
Classifier: Development Status :: 3 - Alpha
Classifier: License :: OSI Approved :: BSD License
Classifier: Natural Language :: English
Classifier: Programming Language :: Python :: 3
Classifier: Programming Language :: Python :: 3.9
Classifier: Programming Language :: Python :: 3.10
Classifier: Programming Language :: Python :: 3.11
Classifier: Programming Language :: Python :: 3.12
Classifier: Programming Language :: Python :: 3.13
Classifier: Typing :: Typed
Requires-Python: >=3.9
License-File: LICENSE
Requires-Dist: numpy
Requires-Dist: numba
Requires-Dist: matplotlib
Requires-Dist: torch
Requires-Dist: imageio
Requires-Dist: cmasher
Requires-Dist: scipy
Requires-Dist: pandas
Requires-Dist: scikit-image
Requires-Dist: scikit-learn
Requires-Dist: tqdm
Provides-Extra: demo
Requires-Dist: h5py; extra == "demo"
Requires-Dist: jupyterlab; extra == "demo"
Requires-Dist: pooch; extra == "demo"
Provides-Extra: test
Requires-Dist: pytest>=6.0; extra == "test"
Requires-Dist: pytest-cov; extra == "test"
Provides-Extra: dev
Requires-Dist: ipython; extra == "dev"
Requires-Dist: mypy; extra == "dev"
Requires-Dist: pdbpp; extra == "dev"
Requires-Dist: pre-commit; extra == "dev"
Requires-Dist: rich; extra == "dev"
Requires-Dist: ruff; extra == "dev"
Requires-Dist: check-manifest; extra == "dev"
Requires-Dist: sisal[test]; extra == "dev"
Dynamic: license-file
